agentid/__init__.py
agentid/client.py
agentid/crypto.py
agentid/errors.py
agentid/py.typed
agentid/types.py
agentid/verify.py
agentid-1.0.0.dist-info/METADATA
agentid-1.0.0.dist-info/WHEEL
agentid-1.0.0.dist-info/RECORD
