Metadata-Version: 2.4
Name: agentid
Version: 1.0.0
Summary: Python SDK for verifying AI agent credentials issued by AgentID
Project-URL: Homepage, https://agentid.dev
Project-URL: Documentation, https://docs.agentid.dev/python-sdk
Project-URL: Repository, https://github.com/agentid/agentid-python
Author-email: AgentID <sdk@agentid.dev>
License: MIT
Keywords: agents,ai,credentials,ed25519,verification
Classifier: Development Status :: 4 - Beta
Classifier: Intended Audience :: Developers
Classifier: License :: OSI Approved :: MIT License
Classifier: Programming Language :: Python :: 3
Classifier: Programming Language :: Python :: 3.9
Classifier: Programming Language :: Python :: 3.10
Classifier: Programming Language :: Python :: 3.11
Classifier: Programming Language :: Python :: 3.12
Classifier: Topic :: Security :: Cryptography
Classifier: Topic :: Software Development :: Libraries :: Python Modules
Classifier: Typing :: Typed
Requires-Python: >=3.9
Requires-Dist: httpx>=0.25.0
Requires-Dist: pydantic>=2.0.0
Requires-Dist: pynacl>=1.5.0
Provides-Extra: dev
Requires-Dist: mypy>=1.0.0; extra == 'dev'
Requires-Dist: pytest-asyncio>=0.21.0; extra == 'dev'
Requires-Dist: pytest>=7.0.0; extra == 'dev'
Requires-Dist: ruff>=0.1.0; extra == 'dev'
